MANIFEST.in
README.rst
setup.py
surt/DefaultIAURLCanonicalizer.py
surt/GoogleURLCanonicalizer.py
surt/IAURLCanonicalizer.py
surt/URLRegexTransformer.py
surt/__init__.py
surt/handyurl.py
surt/surt.py
surt.egg-info/PKG-INFO
surt.egg-info/SOURCES.txt
surt.egg-info/dependency_links.txt
surt.egg-info/requires.txt
surt.egg-info/top_level.txt
surt.egg-info/zip-safe