Metadata-Version: 1.1
Name: surt
Version: 0.3b4
Summary: Sort-friendly URI Reordering Transform (SURT) python package.
Home-page: https://github.com/internetarchive/surt
Author: rajbot
Author-email: raj@archive.org
License: UNKNOWN
Platform: UNKNOWN
Classifier: License :: OSI Approved :: GNU Affero General Public License v3
Provides: surt
